[{
  "name": "Niclas Superlongsurname",

  "marriages": [{
    "spouse": {
      "name": "Iliana",
      "class": "woman"
    },
    "children": [{
      "name": "James",
      "marriages": [{
        "spouse": {
          "name": "Alexandra",
          "class": "woman"
        },
        "children": [{
          "name": "Eric",
          "class": "man",
          "marriages": [{
            "spouse": {
              "name": "Eva",
              "class": "woman"
            }
          }]
        }, {
          "name": "Jane",
          "class": "woman"
        }, {
          "name": "Jasper",
          "class": "man"
        }, {
          "name": "Emma",
          "class": "woman"
        }, {
          "name": "Julia",
          "class": "woman"
        }, {
          "name": "Jessica",
          "class": "woman"
        }]
      }]
    }]
  }]
}]
